sphinxcontrib/__init__.py
sphinxcontrib/git_context.py
sphinxcontrib_git_context-0.1.0.dist-info/AUTHORS.rst
sphinxcontrib_git_context-0.1.0.dist-info/LICENSE.txt
sphinxcontrib_git_context-0.1.0.dist-info/METADATA
sphinxcontrib_git_context-0.1.0.dist-info/WHEEL
sphinxcontrib_git_context-0.1.0.dist-info/top_level.txt
sphinxcontrib_git_context-0.1.0.dist-info/RECORD
